pyvantagepro2/__init__.py
pyvantagepro2/__main__.py
pyvantagepro2/compat.py
pyvantagepro2/device.py
pyvantagepro2/logger.py
pyvantagepro2/parser.py
pyvantagepro2/utils.py
PyVantagePro2-0.0.7.dist-info/METADATA
PyVantagePro2-0.0.7.dist-info/WHEEL
PyVantagePro2-0.0.7.dist-info/entry_points.txt
PyVantagePro2-0.0.7.dist-info/top_level.txt
PyVantagePro2-0.0.7.dist-info/RECORD
